{
  "_id": "jHFLBXISDVvtHjkZ",
  "_key": "!item!bg-attaccabrigheabito-comune-57781c",
  "name": "Abito comune",
  "type": "equipment",
  "img": "icons/equipment/chest/shirt-simple-white.webp",
  "system": {
    "description": {
      "value": "<p>Abito comune - Equipaggiamento iniziale del background attaccabrighe.</p>"
    },
    "source": {
      "custom": "Brancalonia"
    },
    "quantity": 1,
    "weight": 0,
    "price": {
      "value": 0,
      "denomination": "gp"
    },
    "identified": true,
    "rarity": "common",
    "armor": {
      "value": 10,
      "dex": null
    },
    "speed": {
      "value": null
    },
    "strength": 0,
    "stealth": false,
    "type": {
      "value": "trinket"
    },
    "identifier": "bg-attaccabrigheabito-comune-57781c",
    "equipped": false
  },
  "effects": [],
  "folder": null,
  "sort": 0,
  "ownership": {
    "default": 0
  },
  "flags": {
    "brancalonia": {
      "tipo": "equipaggiamento_background",
      "background": "attaccabrighe"
    }
  }
}