{
  "_id": "classguerrierolivello9indomitof05437",
  "_key": "!items!classguerrierolivello9indomitof05437",
  "name": "Indomito",
  "type": "feat",
  "img": "icons/skills/yellow/affinity-puzzle.webp",
  "system": {
    "description": {
      "value": "<p>A partire dal 9° livello, puoi ritirare un tiro salvezza che hai fallito. Se lo fai, devi usare il nuovo tiro, e non puoi usare questa capacità di nuovo fino a che non finisci un riposo lungo.</p>",
      "chat": "",
      "unidentified": ""
    },
    "source": "Brancalonia Manuale Base, D&D 5e PHB p.72",
    "activation": {
      "type": "",
      "cost": null,
      "condition": ""
    },
    "duration": {
      "value": "",
      "units": ""
    },
    "target": {
      "value": null,
      "width": null,
      "units": "",
      "type": ""
    },
    "range": {
      "value": null,
      "long": null,
      "units": ""
    },
    "uses": {
      "value": null,
      "max": "",
      "per": null,
      "recovery": ""
    },
    "equipped": false,
    "identified": true,
    "quantity": 1,
    "weight": 0,
    "price": {
      "value": 0,
      "denomination": "gp"
    },
    "rarity": "common",
    "attunement": 0,
    "requirements": "",
    "type": {
      "value": "class",
      "subtype": ""
    },
    "recharge": {
      "value": null,
      "charged": false
    }
  },
  "effects": [],
  "folder": null,
  "sort": 0,
  "ownership": {
    "default": 0
  },
  "flags": {
    "brancalonia": {
      "id_originale": "class-guerriero-livello_9-indomito",
      "fonte": "Brancalonia Manuale Base, D&D 5e PHB p.72"
    }
  }
}