{
  "_id": "7b5c9b1a6571371c",
  "_key": "!item!7b5c9b1a6571371c",
  "name": "Indomabile (1 uso)",
  "type": "feat",
  "img": "icons/skills/melee/strike-sword-steel-yellow.webp",
  "system": {
    "description": {
      "value": "<p>Puoi ritirare un tiro salvezza fallito. Una volta usato, devi completare un riposo lungo.</p>",
      "chat": "",
      "unidentified": ""
    },
    "source": "Player's Handbook (D&D 5e)",
    "activation": {
      "type": "",
      "cost": null,
      "condition": ""
    },
    "duration": {
      "value": "",
      "units": ""
    },
    "target": {
      "value": null,
      "width": null,
      "units": "",
      "type": ""
    },
    "range": {
      "value": null,
      "long": null,
      "units": ""
    },
    "uses": {
      "value": null,
      "max": "",
      "per": null,
      "recovery": ""
    },
    "equipped": false,
    "identified": true,
    "quantity": 1,
    "weight": 0,
    "price": {
      "value": 0,
      "denomination": "gp"
    },
    "rarity": "common",
    "attunement": 0,
    "requirements": "Guerriero Livello 9",
    "type": {
      "value": "class",
      "subtype": ""
    },
    "recharge": {
      "value": null,
      "charged": false
    }
  },
  "effects": [],
  "folder": null,
  "sort": 0,
  "ownership": {
    "default": 0
  },
  "flags": {
    "brancalonia-bigat": {
      "classe": "guerriero",
      "livello": 9
    }
  }
}