{
  "_id": "bg-impresarioborsa-con-20-ma-992eda",
  "_key": "!item!bg-impresarioborsa-con-20-ma-992eda",
  "name": "Borsa con 20 ma",
  "type": "equipment",
  "img": "icons/containers/bags/sack-simple-leather-brown.webp",
  "system": {
    "description": {
      "value": "<p>Borsa con 20 ma - Equipaggiamento iniziale del background impresario.</p>",
      "chat": "",
      "unidentified": ""
    },
    "source": {
      "custom": "Brancalonia"
    },
    "quantity": 1,
    "weight": 2,
    "price": {
      "value": 0,
      "denomination": "gp"
    },
    "identified": true,
    "rarity": "common",
    "capacity": {
      "type": "weight",
      "value": 30
    },
    "currency": {
      "cp": 0,
      "sp": 200,
      "ep": 0,
      "gp": 0,
      "pp": 0
    },
    "attunement": "",
    "armor": {
      "type": "trinket",
      "value": null,
      "dex": null
    },
    "type": {
      "value": "trinket",
      "baseItem": ""
    }
  },
  "effects": [],
  "folder": null,
  "sort": 0,
  "ownership": {
    "default": 0
  },
  "flags": {
    "brancalonia": {
      "tipo": "equipaggiamento_background",
      "background": "impresario"
    }
  }
}